README.md
setup.cfg
setup.py
THP_Sensing/__init__.py
THP_Sensing/datamgmt.py
THP_Sensing/displaythp.py
THP_Sensing/jsondata.py
THP_Sensing/mainthp.py
THP_Sensing/test.py
THP_Sensing/thpsensing.py
THP_Sensing.egg-info/PKG-INFO
THP_Sensing.egg-info/SOURCES.txt
THP_Sensing.egg-info/dependency_links.txt
THP_Sensing.egg-info/requires.txt
THP_Sensing.egg-info/top_level.txt