Metadata-Version: 2.1
Name: THP-Sensing
Version: 0.2.2
Summary: Weather Monitoring
Home-page: https://github.com/Prabhuprasadbiswal
Author: Prabhu Prasad Biswal
Author-email: prabhuprasadbiswal5@gmail.com
License: IISERm
Keywords: weather,Temperature,Pressure,Humidity
Platform: UNKNOWN
Requires-Python: >=3.7
